{"_id":null,"field_test_unique_id":"/Users/sigtrak/testdata/regressions/pcixp_rev1_ep_0.8/1/ep_txn_5_3_6","field_test_result":"FAILED","field_test_error":"[62944] ERROR:  EP Received Packet 3 Not MATCHED.  ","field_test_directory":"/Users/sigtrak/testdata/regressions/pcixp_rev1_ep_0.8/1","field_test_regression":"pcixp_rev1_ep_0.8/1","field_test_directory_date":"03/03/2016 03:37:05","field_test_project":"pcixp_rev1","field_test_module":"ep","field_test_release":"0.8","field_test_sim_time":152084,"field_test_time_completed":"29/12/2015 17:43:38","field_test_name":"ep_txn_5_3_6","field_test_seed":0,"field_build_seed":0}